streamlit_datetime_picker/__init__.py
streamlit_datetime_picker/example.py
streamlit_datetime_picker/frontend/build/asset-manifest.json
streamlit_datetime_picker/frontend/build/favicon.ico
streamlit_datetime_picker/frontend/build/index.html
streamlit_datetime_picker/frontend/build/manifest.json
streamlit_datetime_picker/frontend/build/robots.txt
streamlit_datetime_picker/frontend/build/static/js/main.a6d7cf34.js
streamlit_datetime_picker/frontend/build/static/js/main.a6d7cf34.js.LICENSE.txt
streamlit_datetime_picker/frontend/build/static/js/main.a6d7cf34.js.map
streamlit_datetime_picker-0.0.2.dist-info/LICENSE
streamlit_datetime_picker-0.0.2.dist-info/METADATA
streamlit_datetime_picker-0.0.2.dist-info/WHEEL
streamlit_datetime_picker-0.0.2.dist-info/top_level.txt
streamlit_datetime_picker-0.0.2.dist-info/RECORD
